mlmetrics/__init__.py
mlmetrics/preprocessing.py
mlmetrics/ranking.py
mlmetrics/rating.py
MLMetrics-0.2.dist-info/METADATA
MLMetrics-0.2.dist-info/WHEEL
MLMetrics-0.2.dist-info/entry_points.txt
MLMetrics-0.2.dist-info/top_level.txt
MLMetrics-0.2.dist-info/RECORD
